[

  {
    "id": "es_a1_ser_estar_01",
    "type": "concept",
    "title": "¿Ser o Estar? — Due verbi che conosci già (quasi)",
    "bridge": "Ottima notizia: nella tua lingua esistono già due verbi, 'essere' e 'stare', che corrispondono in parte a 'ser' e 'estar'. Il problema è che la corrispondenza non è perfetta — e proprio lì si nascondono le trappole. 'Ser' ≈ essere (identità, origine). 'Estar' ≈ stare (stati, emozioni). Ma in italiano usi 'essere' anche per la posizione ('sono a Roma'), mentre in spagnolo lì va 'estar'. Questa differenza è il cuore dell'errore più comune.",
    "rule": "Usa 'ser' per ciò che definisce chi sei: nome, nazionalità, professione, caratteristiche permanenti. Usa 'estar' per dove sei e come ti senti: luogo, stati temporanei, emozioni.",
    "common_error": {
      "wrong": "Sono in Italia. (traduzione diretta dall'italiano)",
      "example_1": "Soy italiano. (nazionalità = identità = ser)",
      "example_2": "Estoy en Italia. (posizione nello spazio = estar)",
      "explanation": "In italiano dici 'sono a Roma' con 'essere'. In spagnolo la posizione fisica di persone e oggetti usa sempre 'estar', non 'ser'. È la differenza più difficile per chi parla italiano: 'essere' in italiano copre anche il luogo, ma 'ser' in spagnolo no."
    },
    "levels": [
      {
        "level": 1,
        "label": "Soy / Estoy — lo básico",
        "translation": "Soy / Estoy — le basi",
        "examples": [
          {
            "original": "Soy Marco.",
            "translation": "Sono Marco.",
            "note": "Il nome proprio definisce l'identità → 'ser'. Come 'essere' in italiano per il nome."
          },
          {
            "original": "Estoy aquí.",
            "translation": "Sono qui.",
            "note": "La posizione nello spazio → 'estar'. Attenzione: in italiano si usa 'essere', ma in spagnolo si usa 'estar'."
          },
          {
            "original": "Soy italiano.",
            "translation": "Sono italiano.",
            "note": "La nazionalità è un'identità permanente → 'ser'."
          }
        ]
      },
      {
        "level": 2,
        "label": "Profesión y estado de ánimo",
        "translation": "Professione e stato d'animo",
        "examples": [
          {
            "original": "Soy médico.",
            "translation": "Sono medico.",
            "note": "La professione definisce chi sei → 'ser'. Come 'essere' in italiano."
          },
          {
            "original": "Estoy cansado.",
            "translation": "Sono stanco.",
            "note": "La stanchezza è temporanea → 'estar'. In italiano 'essere stanco' usa 'essere', ma in spagnolo usa 'estar'."
          },
          {
            "original": "Estoy bien, gracias.",
            "translation": "Sto bene, grazie.",
            "note": "Stato di salute → 'estar'. Questa volta coincide con l'italiano 'stare bene' → 'estar bien'. Uno dei casi in cui la corrispondenza è perfetta!"
          }
        ]
      },
      {
        "level": 3,
        "label": "Casos que van a sorprender",
        "translation": "Casi che ti sorprenderanno",
        "examples": [
          {
            "original": "La pasta es buena. / La pasta está buena.",
            "translation": "La pasta è buona (in generale). / La pasta è buona (adesso, questa qui).",
            "note": "Stesso aggettivo, significato diverso! 'Ser' = caratteristica intrinseca; 'estar' = stato attuale. Utilissimo al ristorante."
          },
          {
            "original": "Es aburrido. / Está aburrido.",
            "translation": "È noioso (di carattere). / Si sta annoiando (in questo momento).",
            "note": "La scelta del verbo cambia completamente il senso. 'Ser' = tratto permanente; 'estar' = stato momentaneo."
          },
          {
            "original": "Está muerto.",
            "translation": "È morto.",
            "note": "Sorprendente: la morte sembra permanente, ma è il risultato di un cambiamento di stato → 'estar'. Da memorizzare così."
          }
        ]
      }
    ],
    "emoji": "🔀",
    "phonetic": "",
    "translations": { "it": "Essere (identità) vs Essere (stato / luogo)" }
  },

  {
    "id": "es_a1_ser_estar_02",
    "type": "concept",
    "title": "Ser — para describir lo que eres",
    "bridge": "Pensa a 'ser' come al verbo delle risposte a 'Chi sei?'. Funziona come 'essere' in italiano per: nome, nazionalità, professione, aspetto fisico stabile, personalità, relazioni familiari, e anche per l'ora e le date. La trappola: in italiano 'essere' fa anche il lavoro di 'estar' per la posizione — 'ser' invece no.",
    "rule": "Usa 'ser' per: nome, nazionalità, professione, descrizione fisica stabile, carattere, relazioni familiari, ora e date. Tutto ciò che risponde a 'Chi sei?' o 'Com'è?'.",
    "common_error": {
      "wrong": "Soy en Roma.",
      "example_1": "Soy romano. (origine/nazionalità = ser)",
      "example_2": "Estoy en Roma. (posizione fisica = estar)",
      "explanation": "In italiano 'sono a Roma' usa 'essere', e viene spontaneo tradurre con 'soy'. Ma in spagnolo la posizione fisica vuole sempre 'estar'. 'Ser' + luogo non esiste (tranne per gli eventi: 'la fiesta es aquí')."
    },
    "levels": [
      {
        "level": 1,
        "label": "Origen y profesión",
        "translation": "Origine e professione",
        "examples": [
          {
            "original": "Soy de Milán.",
            "translation": "Sono di Milano.",
            "note": "L'origine geografica non cambia → 'ser'. Come 'essere' in italiano."
          },
          {
            "original": "Soy ingeniero.",
            "translation": "Sono ingegnere.",
            "note": "La professione definisce l'identità → 'ser'. Nota: nessun articolo dopo 'ser' per le professioni."
          }
        ]
      },
      {
        "level": 2,
        "label": "Descripción y personalidad",
        "translation": "Descrizione e personalità",
        "examples": [
          {
            "original": "Soy alto y delgado.",
            "translation": "Sono alto e magro.",
            "note": "Caratteristiche fisiche stabili → 'ser'. Coincide con 'essere' in italiano."
          },
          {
            "original": "Ella es muy simpática.",
            "translation": "Lei è molto simpatica.",
            "note": "Un tratto del carattere permanente → 'ser'. Come 'essere' in italiano."
          },
          {
            "original": "Somos amigos.",
            "translation": "Siamo amici.",
            "note": "Le relazioni sociali durature → 'ser'."
          }
        ]
      },
      {
        "level": 3,
        "label": "La hora y las fechas",
        "translation": "L'ora e le date",
        "examples": [
          {
            "original": "Son las tres.",
            "translation": "Sono le tre.",
            "note": "L'ora si esprime con 'ser', mai con 'estar'. 'Es la una' (singolare) / 'Son las dos, las tres…' (plurale). Coincide con 'essere' in italiano."
          },
          {
            "original": "Hoy es lunes.",
            "translation": "Oggi è lunedì.",
            "note": "Il giorno della settimana usa 'ser'. Come in italiano 'è lunedì'."
          },
          {
            "original": "La reunión es el martes.",
            "translation": "La riunione è martedì.",
            "note": "Il momento di un evento → 'ser'. Come 'essere' in italiano per appuntamenti e date."
          }
        ]
      }
    ],
    "emoji": "🆔",
    "phonetic": "",
    "translations": { "it": "Ser — per descrivere chi sei" }
  },

  {
    "id": "es_a1_ser_estar_03",
    "type": "concept",
    "title": "Estar — para decir cómo estás y dónde estás",
    "bridge": "Pensa a 'estar' come alla fusione di 'stare' e di 'essere' quando indica posizione. In italiano dici 'sto bene' (stare) MA anche 'sono a Roma' (essere). In spagnolo entrambe le situazioni usano 'estar': 'estoy bien' E 'estoy en Roma'. Questa è la differenza chiave da ricordare.",
    "rule": "Usa 'estar' per: posizione fisica (persone e oggetti), stato di salute, emozioni e stati temporanei, e per formare il presente progressivo (estar + gerundio).",
    "common_error": {
      "wrong": "El museo es en el centro.",
      "example_1": "La reunión es en el museo. (luogo di un evento = ser)",
      "example_2": "El museo está en el centro. (posizione fisica dell'edificio = estar)",
      "explanation": "Edifici, persone e oggetti usano 'estar' per la loro posizione. L'eccezione: il luogo di un evento (festa, riunione) usa 'ser'. In italiano entrambi userebbero 'essere' — in spagnolo si distinguono."
    },
    "levels": [
      {
        "level": 1,
        "label": "¿Dónde estás?",
        "translation": "Dove sei?",
        "examples": [
          {
            "original": "Estoy en casa.",
            "translation": "Sono a casa.",
            "note": "Posizione fisica di una persona → 'estar'. In italiano 'sono a casa' usa 'essere' — in spagnolo usa 'estar'."
          },
          {
            "original": "El libro está en la mesa.",
            "translation": "Il libro è sul tavolo.",
            "note": "Posizione di un oggetto → 'estar'. Attenzione: in italiano 'è sul tavolo' usa 'essere', ma in spagnolo usa 'estar'."
          }
        ]
      },
      {
        "level": 2,
        "label": "Emociones y estados",
        "translation": "Emozioni e stati",
        "examples": [
          {
            "original": "Estoy nervioso.",
            "translation": "Sono nervoso.",
            "note": "Un'emozione momentanea → 'estar'. In italiano 'essere nervoso' usa 'essere', ma in spagnolo usa 'estar'."
          },
          {
            "original": "La puerta está abierta.",
            "translation": "La porta è aperta.",
            "note": "Lo stato di un oggetto (risultato di un'azione) → 'estar'. La porta può essere anche chiusa."
          },
          {
            "original": "Estamos de vacaciones.",
            "translation": "Siamo in vacanza.",
            "note": "Situazione temporanea → 'estar'. In italiano 'siamo in vacanza' usa 'essere'."
          }
        ]
      },
      {
        "level": 3,
        "label": "Excepción: eventos y edificios",
        "translation": "Eccezione: eventi e edifici",
        "examples": [
          {
            "original": "La fiesta es en mi casa.",
            "translation": "La festa è a casa mia.",
            "note": "Il luogo di un evento → 'ser'. L'evento ha un'identità nel tempo. Eccezione alla regola della posizione."
          },
          {
            "original": "Mi casa está en Madrid.",
            "translation": "La mia casa è a Madrid.",
            "note": "La posizione di un edificio → 'estar'. Confronta questi due esempi: stesso 'casa', verbi diversi."
          },
          {
            "original": "¿Dónde está el baño?",
            "translation": "Dov'è il bagno?",
            "note": "Frase di sopravvivenza assoluta! Posizione di un luogo → 'estar'. In italiano 'dov'è' usa 'essere'."
          }
        ]
      }
    ],
    "emoji": "📍",
    "phonetic": "",
    "translations": { "it": "Estar — per dire come stai e dove sei" }
  },


  {
    "id": "es_a1_articulos_01",
    "type": "concept",
    "title": "El / La — el artículo cambia según el género",
    "bridge": "Nella tua lingua hai già 'il/lo/la' per il maschile e femminile. In spagnolo è ancora più semplice: solo 'el' per il maschile e 'la' per il femminile (niente 'lo'!). La logica è la stessa, ma attenzione: il genere di alcune parole è diverso tra le due lingue.",
    "rule": "Usa 'el' davanti ai nomi maschili e 'la' davanti ai femminili. Plurale: 'los' (masch.) e 'las' (femm.). Non esiste il neutro né forme come 'lo' o 'gli'.",
    "common_error": {
      "wrong": "Lo problema è difficile.",
      "example_1": "El problema es difícil. (problema = maschile, anche se finisce in -a)",
      "example_2": "",
      "explanation": "'Problema' finisce in '-a' ma è maschile in spagnolo (origine greca). Inoltre, 'lo' non esiste come articolo determinativo in spagnolo — solo 'el'. L'errore tipico degli italiani è usare 'lo' davanti a consonanti particolari, come si fa in italiano."
    },
    "levels": [
      {
        "level": 1,
        "label": "El / La — masculino y femenino",
        "translation": "El / La — maschile e femminile",
        "examples": [
          {
            "original": "el libro",
            "translation": "il libro",
            "note": "'Libro' finisce in '-o' → di solito maschile → 'el'. Come in italiano."
          },
          {
            "original": "la mesa",
            "translation": "il tavolo / la tavola",
            "note": "'Mesa' finisce in '-a' → di solito femminile → 'la'. Nota: 'tavolo' in italiano è maschile, 'mesa' in spagnolo è femminile. Il genere può differire!"
          },
          {
            "original": "el hombre / la mujer",
            "translation": "l'uomo / la donna",
            "note": "Il genere biologico corrisponde al genere grammaticale."
          }
        ]
      },
      {
        "level": 2,
        "label": "Plural: los / las",
        "translation": "Plurale: los / las",
        "examples": [
          {
            "original": "los libros",
            "translation": "i libri",
            "note": "'Los' è il plurale di 'el'. Non esiste 'gli' o 'i' separati — solo 'los' per tutto il maschile."
          },
          {
            "original": "las mesas",
            "translation": "i tavoli / le tavole",
            "note": "'Las' è il plurale di 'la'. Più semplice dell'italiano: non c'è distinzione tra 'le' e 'i'/'gli'."
          }
        ]
      },
      {
        "level": 3,
        "label": "Géneros distintos del italiano",
        "translation": "Generi diversi dall'italiano",
        "examples": [
          {
            "original": "el puente",
            "translation": "il ponte",
            "note": "Maschile in entrambe le lingue → facile. Ma occhio: non sempre coincidono."
          },
          {
            "original": "el agua / las aguas",
            "translation": "l'acqua / le acque",
            "note": "Femminile ma si dice 'el agua' al singolare (per evitare due 'a' consecutive). Al plurale torna 'las aguas'. Eccezione da memorizzare."
          },
          {
            "original": "la mano",
            "translation": "la mano",
            "note": "Finisce in '-o' ma è femminile! Come in italiano 'la mano'. Uno dei rari casi in cui le due lingue concordano su un'eccezione."
          }
        ]
      }
    ],
    "emoji": "🏷️",
    "phonetic": "",
    "translations": { "it": "El / La — l'articolo cambia secondo il genere" }
  },

  {
    "id": "es_a1_articulos_02",
    "type": "concept",
    "title": "Un / Una — artículos indefinidos",
    "bridge": "Nella tua lingua hai 'un/uno' per il maschile e 'una/un'' per il femminile. In spagnolo è quasi identico: 'un' (maschile) e 'una' (femminile). L'unica differenza: niente 'uno' — solo 'un' per il maschile. È probabilmente la parte più facile per te!",
    "rule": "Usa 'un' davanti a un nome maschile e 'una' davanti a un femminile quando parli di qualcosa di non specifico o menzionato per la prima volta. Plurale: 'unos / unas' (equivalente di 'alcuni/alcune').",
    "common_error": {
      "wrong": "Tengo uno problema.",
      "example_1": "Tengo un problema. (maschile = un, non uno)",
      "example_2": "",
      "explanation": "In italiano si dice 'uno problema' quando la parola comincia per consonante impura o 's+consonante'. In spagnolo non esiste questa regola: l'articolo maschile indefinito è sempre 'un', mai 'uno'."
    },
    "levels": [
      {
        "level": 1,
        "label": "Un / Una — presentar algo nuevo",
        "translation": "Un / Una — presentare qualcosa di nuovo",
        "examples": [
          {
            "original": "un perro",
            "translation": "un cane",
            "note": "'Perro' è maschile → 'un'. Come in italiano, ma senza la forma 'uno'."
          },
          {
            "original": "una casa",
            "translation": "una casa",
            "note": "'Casa' è femminile → 'una'. Identico all'italiano!"
          },
          {
            "original": "Tengo un gato y una tortuga.",
            "translation": "Ho un gatto e una tartaruga.",
            "note": "L'accordo si fa separatamente per ogni nome secondo il suo genere."
          }
        ]
      },
      {
        "level": 2,
        "label": "Definido vs. indefinido",
        "translation": "Determinativo vs. indeterminativo",
        "examples": [
          {
            "original": "Hay un café en la plaza.",
            "translation": "C'è un bar in piazza.",
            "note": "'Un' = lo menzione per la prima volta, non sai quale. Come 'un' in italiano."
          },
          {
            "original": "El café está cerrado.",
            "translation": "Il bar è chiuso.",
            "note": "'El' = ora sappiamo di quale bar si tratta (quello menzionato prima). Il determinativo sostituisce l'indeterminativo."
          }
        ]
      },
      {
        "level": 3,
        "label": "Cuándo se omite el artículo",
        "translation": "Quando si omette l'articolo",
        "examples": [
          {
            "original": "Soy médico. (sin artículo)",
            "translation": "Sono medico. (senza articolo)",
            "note": "Dopo 'ser' per la professione → nessun articolo! Come in italiano 'sono medico' (non 'sono un medico' nella forma neutra). La regola coincide."
          },
          {
            "original": "No tengo coche.",
            "translation": "Non ho la macchina. / Non ho un'auto.",
            "note": "Dopo una negazione, l'articolo indeterminativo spesso sparisce. Simile all'italiano ma più sistematico."
          }
        ]
      }
    ],
    "emoji": "1️⃣",
    "phonetic": "",
    "translations": { "it": "Un / Una — articoli indeterminativi" }
  },

  {
    "id": "es_a1_articulos_03",
    "type": "concept",
    "title": "El género de las palabras — ¿cómo saberlo?",
    "bridge": "Nella tua lingua il genere delle parole si impara spesso a memoria, con alcune regole di terminazione. In spagnolo le regole sono ancora più regolari: '-o' quasi sempre maschile, '-a' quasi sempre femminile. Il rischio per te è assumere che il genere sia identico all'italiano — non è sempre così!",
    "rule": "Regola generale: parole in '-o' → maschili (el libro); parole in '-a' → femminili (la mesa). Terminazioni come '-dad', '-ción', '-sión' sono sempre femminili. Impara ogni parola con il suo articolo.",
    "common_error": {
      "wrong": "el calor / el color — (maschili, come in italiano ✓) vs el puente / la puente",
      "example_1": "el puente ✓ (maschile in spagnolo come in italiano)",
      "example_2": "la canción ✓ (femminile, terminazione -ción = sempre femminile)",
      "explanation": "La maggior parte dei generi coincide tra le due lingue, ma ci sono eccezioni importanti. Esempi di generi diversi: 'il caldo' (masc. in italiano) → 'el calor' (masc. in spagnolo ✓). Ma 'il sale' (masc.) → 'la sal' (femm. in spagnolo ✗). Vale la pena imparare ogni parola con il suo articolo."
    },
    "levels": [
      {
        "level": 1,
        "label": "Regla -o / -a",
        "translation": "Regola -o / -a",
        "examples": [
          {
            "original": "el niño / la niña",
            "translation": "il bambino / la bambina",
            "note": "La terminazione cambia con il genere biologico: -o maschile, -a femminile. Come in italiano."
          },
          {
            "original": "el amigo / la amiga",
            "translation": "l'amico / l'amica",
            "note": "Identico all'italiano! Una delle aree dove le due lingue si somigliano molto."
          }
        ]
      },
      {
        "level": 2,
        "label": "Terminaciones siempre femeninas",
        "translation": "Terminazioni sempre femminili",
        "examples": [
          {
            "original": "la ciudad",
            "translation": "la città",
            "note": "Terminazione '-dad' → sempre femminile. Esempi: la verdad, la libertad, la realidad. Come '-tà' in italiano (la città, la libertà) → stesso genere!"
          },
          {
            "original": "la canción",
            "translation": "la canzone",
            "note": "Terminazione '-ción' → sempre femminile. Come '-zione' in italiano (la nazione, la situazione) → stesso genere!"
          }
        ]
      },
      {
        "level": 3,
        "label": "Generos diferentes al italiano",
        "translation": "Generi diversi dall'italiano",
        "examples": [
          {
            "original": "la sal",
            "translation": "il sale → la sal (femminile!)",
            "note": "'Sale' in italiano è maschile, 'sal' in spagnolo è femminile. Uno dei casi in cui il genere diverge."
          },
          {
            "original": "el día",
            "translation": "il giorno → el día (maschile!)",
            "note": "Finisce in '-a' ma è maschile. Come in italiano 'il giorno' è maschile. Eccezione importante: anche 'el mapa', 'el problema', 'el idioma' (origine greca)."
          }
        ]
      }
    ],
    "emoji": "⚥",
    "phonetic": "",
    "translations": { "it": "Il genere delle parole — come riconoscerlo?" }
  },


  {
    "id": "es_a1_reflexivos_01",
    "type": "concept",
    "title": "Me llamo… — i verbi riflessivi, già li conosci",
    "bridge": "Nella tua lingua hai già i verbi riflessivi: 'mi chiamo', 'mi alzo', 'mi lavo'. In spagnolo funziona quasi identicamente: 'me llamo', 'me levanto', 'me lavo'. I pronomi riflessivi (me, te, se, nos, os, se) si accordano con il soggetto, esattamente come in italiano (mi, ti, si, ci, vi, si). È probabilmente l'argomento più facile per te!",
    "rule": "Verbo riflessivo = azione che il soggetto fa su se stesso. Il pronome riflessivo si mette prima del verbo coniugato: me, te, se, nos, os, se. Corrispondenza con l'italiano: mi→me, ti→te, si→se, ci→nos, vi→os.",
    "common_error": {
      "wrong": "Mi llamo Marco. (copia diretta dall'italiano)",
      "example_1": "Me llamo Marco. (il pronome riflessivo spagnolo è 'me', non 'mi')",
      "example_2": "",
      "explanation": "La struttura è identica all'italiano, ma il pronome cambia: in italiano 'mi chiamo', in spagnolo 'me llamo'. Non 'mi llamo'! Il cambio 'mi→me' è la trappola più frequente per chi parla italiano."
    },
    "levels": [
      {
        "level": 1,
        "label": "Me llamo / Te llamas",
        "translation": "Mi chiamo / Ti chiami",
        "examples": [
          {
            "original": "Me llamo Juan.",
            "translation": "Mi chiamo Juan.",
            "note": "Struttura identica all'italiano, ma 'mi' diventa 'me'. Facile da ricordare una volta notata la differenza."
          },
          {
            "original": "¿Cómo te llamas?",
            "translation": "Come ti chiami?",
            "note": "'Ti' in italiano → 'te' in spagnolo. Il pronome di 2ª persona cambia forma."
          },
          {
            "original": "Ella se llama Sofía.",
            "translation": "Lei si chiama Sofía.",
            "note": "'Si' in italiano → 'se' in spagnolo. Il pronome riflessivo di 3ª persona."
          }
        ]
      },
      {
        "level": 2,
        "label": "Pronombres reflexivos completos",
        "translation": "Pronomi riflessivi completi",
        "examples": [
          {
            "original": "Me lavo. / Te lavas. / Se lava.",
            "translation": "Mi lavo. / Ti lavi. / Si lava.",
            "note": "La corrispondenza è quasi perfetta: mi→me, ti→te, si→se. Solo la forma cambia leggermente."
          },
          {
            "original": "Nos levantamos a las ocho.",
            "translation": "Ci alziamo alle otto.",
            "note": "'Ci' in italiano → 'nos' in spagnolo. È il cambiamento più diverso: 'ci' e 'nos' non si somigliano affatto."
          }
        ]
      },
      {
        "level": 3,
        "label": "Verbos que cambian de sentido",
        "translation": "Verbi che cambiano significato",
        "examples": [
          {
            "original": "Llamo a María. / Me llamo María.",
            "translation": "Chiamo María. / Mi chiamo María.",
            "note": "Senza pronome riflessivo: chiamo qualcun altro. Con 'me': mi chiamo. Come in italiano 'chiamare' vs 'chiamarsi'."
          },
          {
            "original": "Voy al mercado. / Me voy.",
            "translation": "Vado al mercato. / Me ne vado.",
            "note": "'Irse' (andarsene) vs 'ir' (andare). Il pronome riflessivo trasforma il significato. Come 'andare' vs 'andarsene' in italiano."
          }
        ]
      }
    ],
    "emoji": "🪞",
    "phonetic": "",
    "translations": { "it": "Verbi riflessivi — azioni che si fanno su se stessi" }
  },

  {
    "id": "es_a1_reflexivos_02",
    "type": "concept",
    "title": "La rutina diaria — verbos reflexivos en acción",
    "bridge": "I verbi della routine quotidiana sono quasi tutti riflessivi in spagnolo, esattamente come in italiano: 'mi sveglio' → 'me despierto', 'mi faccio la doccia' → 'me ducho', 'mi vesto' → 'me visto'. La struttura è identica — solo i pronomi cambiano leggermente di forma.",
    "rule": "I verbi di routine (svegliarsi, lavarsi, vestirsi, alzarsi, coricarsi…) sono riflessivi. Il pronome riflessivo si mette sempre prima del verbo coniugato. Corrispondenza: mi→me, ti→te, si→se, ci→nos, vi→os, si→se.",
    "common_error": {
      "wrong": "Mi sveglio alle sette. / Mi despierto → (pronunciato come italiano)",
      "example_1": "Me despierto a las siete. (pronome 'me', non 'mi')",
      "example_2": "",
      "explanation": "La struttura è identica all'italiano ma il pronome è 'me' non 'mi'. È un errore automatico per chi parla italiano: il cervello produce 'mi despierto' per analogia con 'mi sveglio'. Ricorda: me, te, se, nos, os, se."
    },
    "levels": [
      {
        "level": 1,
        "label": "Verbos de la mañana",
        "translation": "Verbi del mattino",
        "examples": [
          {
            "original": "Me despierto a las siete.",
            "translation": "Mi sveglio alle sette.",
            "note": "'Despertarse' = svegliarsi. Il '-se' nell'infinito indica che è riflessivo, come '-si' in italiano (svegliar-si)."
          },
          {
            "original": "Me ducho rápido.",
            "translation": "Mi faccio la doccia velocemente.",
            "note": "'Ducharse' = fare la doccia. In italiano serve 'fare la doccia' (non riflessivo puro), in spagnolo è semplicemente 'ducharse'."
          },
          {
            "original": "Me visto y salgo.",
            "translation": "Mi vesto ed esco.",
            "note": "'Vestirse' = vestirsi. Struttura identica all'italiano!"
          }
        ]
      },
      {
        "level": 2,
        "label": "A lo largo del día",
        "translation": "Durante la giornata",
        "examples": [
          {
            "original": "Me siento bien hoy.",
            "translation": "Mi sento bene oggi.",
            "note": "'Sentirse' = sentirsi. Perfetta corrispondenza con l'italiano 'sentirsi'."
          },
          {
            "original": "Me acuesto tarde.",
            "translation": "Mi corico tardi.",
            "note": "'Acostarse' = coricarsi. Il verbo spagnolo ha radice diversa ma struttura riflessiva identica."
          }
        ]
      },
      {
        "level": 3,
        "label": "La posición del pronombre",
        "translation": "La posizione del pronome",
        "examples": [
          {
            "original": "Quiero levantarme tarde. / Me quiero levantar tarde.",
            "translation": "Voglio alzarmi tardi.",
            "note": "Con l'infinito, il pronome può attaccarsi alla fine ('levantarme') oppure andare prima del verbo modale ('me quiero'). Entrambe le forme sono corrette. Come in italiano 'voglio alzarmi' o 'mi voglio alzare'."
          },
          {
            "original": "¡Levántate!",
            "translation": "Alzati!",
            "note": "All'imperativo affermativo, il pronome si attacca dopo il verbo. Come in italiano 'alzati!' Uguale struttura!"
          }
        ]
      }
    ],
    "emoji": "⏰",
    "phonetic": "",
    "translations": { "it": "La routine quotidiana — verbi riflessivi in azione" }
  },

  {
    "id": "es_a1_reflexivos_03",
    "type": "concept",
    "title": "Reflexivo vs. no reflexivo — stesso verbo, due sensi",
    "bridge": "In italiano conosci già questa distinzione: 'chiamare' vs 'chiamarsi', 'sentire' vs 'sentirsi', 'alzare' vs 'alzarsi'. In spagnolo funziona esattamente uguale. Anzi, la corrispondenza è così stretta che spesso basta trasferire la logica italiana.",
    "rule": "Molti verbi spagnoli esistono in forma semplice (azione su qualcun altro) e in forma riflessiva (azione su se stessi). Il significato può cambiare radicalmente. Come in italiano.",
    "common_error": {
      "wrong": "Me aburro a mi hermano.",
      "example_1": "Aburro a mi hermano. (yo aburro a alguien = annoio qualcuno)",
      "example_2": "Me aburro en clase. (io mi annoio = sono annoiato)",
      "explanation": "'Aburrir' (annoiare qualcuno) vs 'aburrirse' (annoiarsi). Come in italiano 'annoiare qualcuno' vs 'annoiarsi'. Con 'me', l'azione torna sul soggetto. Non si può usare 'me' e avere un oggetto diretto allo stesso tempo."
    },
    "levels": [
      {
        "level": 1,
        "label": "Pares comunes",
        "translation": "Coppie comuni",
        "examples": [
          {
            "original": "Despierto a mi hijo. / Me despierto.",
            "translation": "Sveglio mio figlio. / Mi sveglio.",
            "note": "Senza 'me': agisco su qualcun altro. Con 'me': agisco su me stesso. Come in italiano."
          },
          {
            "original": "Lavo el coche. / Me lavo.",
            "translation": "Lavo la macchina. / Mi lavo.",
            "note": "Stessa logica: oggetto diretto = qualcosa/qualcuno; pronome riflessivo = me stesso."
          }
        ]
      },
      {
        "level": 2,
        "label": "Verbos con cambio de sentido",
        "translation": "Verbi con cambio di significato",
        "examples": [
          {
            "original": "Pongo el libro aquí. / Me pongo nervioso.",
            "translation": "Metto il libro qui. / Mi innervosisco.",
            "note": "'Ponerse' + aggettivo = diventare (cambiamento di stato). Molto usato per esprimere un cambiamento d'umore. Come 'mettersi' in italiano."
          },
          {
            "original": "¿Vas al cine? / ¿Te vas ya?",
            "translation": "Vai al cinema? / Te ne vai già?",
            "note": "'Irse' = andarsene. Come in italiano 'andare' vs 'andarsene' — il significato diventa più definitivo con il riflessivo."
          }
        ]
      },
      {
        "level": 3,
        "label": "Reflexivos sin equivalente directo",
        "translation": "Riflessivi senza equivalente diretto",
        "examples": [
          {
            "original": "Me alegro de verte.",
            "translation": "Sono contento di vederti.",
            "note": "'Alegrarse' è sempre riflessivo per questo significato. In italiano 'essere contento' non è riflessivo — qui c'è una piccola differenza strutturale."
          },
          {
            "original": "Me arrepiento.",
            "translation": "Mi pento.",
            "note": "'Arrepentirse' = pentirsi. Come in italiano 'pentirsi' — anche qui il riflessivo è obbligatorio. Corrispondenza perfetta."
          }
        ]
      }
    ],
    "emoji": "↔️",
    "phonetic": "",
    "translations": { "it": "Riflessivo vs non riflessivo — stesso verbo, due sensi" }
  },


  {
    "id": "es_a1_tuteo_usted_01",
    "type": "concept",
    "title": "Tú vs. Usted — come il 'tu' e il 'Lei' in italiano",
    "bridge": "Nella tua lingua hai già 'tu' (informale) e 'Lei' (formale). In spagnolo è lo stesso: 'tú' è il tu informale, 'usted' è il Lei formale. La logica sociale è identica. La differenza grammaticale più importante: 'usted' si coniuga come 'él/ella' (3ª persona), esattamente come 'Lei' in italiano si coniuga alla 3ª persona.",
    "rule": "Usa 'tú' con amici, familiari, persone della stessa età. Usa 'usted' con sconosciuti adulti, anziani, professori, e in contesti professionali o formali. 'Usted' si coniuga alla 3ª persona singolare.",
    "common_error": {
      "wrong": "Hola señora, ¿tú tienes mesa para dos?",
      "example_1": "Hola señora, ¿usted tiene mesa para dos? (contesto formale = usted)",
      "example_2": "",
      "explanation": "Dare del 'tu' a una sconosciuta adulta in un ristorante può sembrare scortese. Come in italiano dare del 'tu' a qualcuno che si aspetta il 'Lei'. Usa 'usted' nei contesti formali — è anche un segno di rispetto."
    },
    "levels": [
      {
        "level": 1,
        "label": "¿Tú o usted?",
        "translation": "Tu o Lei?",
        "examples": [
          {
            "original": "¿Tú eres estudiante?",
            "translation": "Tu sei studente?",
            "note": "Tra studenti, 'tú' è la norma. Informale e naturale."
          },
          {
            "original": "¿Usted habla italiano?",
            "translation": "Lei parla italiano?",
            "note": "'Usted' in contesto formale: ufficio, hotel, negozio. Come 'Lei' in italiano."
          }
        ]
      },
      {
        "level": 2,
        "label": "Conjugación: tú vs. usted",
        "translation": "Coniugazione: tu vs. Lei",
        "examples": [
          {
            "original": "¿Tienes tiempo? / ¿Tiene usted tiempo?",
            "translation": "Hai tempo? / Ha tempo?",
            "note": "'Tienes' = 2ª persona (tú). 'Tiene' = 3ª persona (usted). Come in italiano: 'hai' (tu) vs 'ha' (Lei). La logica è identica!"
          },
          {
            "original": "¿Cómo te llamas? / ¿Cómo se llama usted?",
            "translation": "Come ti chiami? / Come si chiama?",
            "note": "Come in italiano: 'ti chiami' (tu) vs 'si chiama' (Lei). Corrispondenza perfetta con il riflessivo."
          }
        ]
      },
      {
        "level": 3,
        "label": "Variaciones regionales",
        "translation": "Variazioni regionali",
        "examples": [
          {
            "original": "Vosotros sois de España. / Ustedes son de México.",
            "translation": "Voi siete dalla Spagna. / Voi siete dal Messico.",
            "note": "In Spagna esiste 'vosotros' (plurale informale di tú). In America Latina non si usa — 'ustedes' fa tutto (formale e informale). Come il 'voi' in italiano che copre entrambi i registri."
          },
          {
            "original": "En Argentina: ¿Vos sos argentino?",
            "translation": "In Argentina: sei argentino?",
            "note": "In Argentina si usa 'vos' al posto di 'tú', con coniugazione diversa. È come un dialetto regionale. Da conoscere se si viaggia in Argentina."
          }
        ]
      }
    ],
    "emoji": "🤝",
    "phonetic": "",
    "translations": { "it": "Tú vs. Usted — come il 'tu' e il 'Lei'" }
  },

  {
    "id": "es_a1_tuteo_usted_02",
    "type": "concept",
    "title": "Usted — la 3.ª persona del respeto",
    "bridge": "In italiano, il 'Lei' formale usa la 3ª persona femminile ('Lei ha', 'Lei viene'). In spagnolo, 'usted' usa la 3ª persona singolare senza distinzione di genere ('usted tiene', come 'él/ella tiene'). La logica è quasi identica — la differenza è che 'usted' è neutro rispetto al genere.",
    "rule": "'Usted' si coniuga come 'él' e 'ella' (3ª persona singolare). 'Ustedes' si coniuga come 'ellos/ellas' (3ª persona plurale). All'scritto si può abbreviare in 'Ud.' o 'Vd.'.",
    "common_error": {
      "wrong": "Usted tienes razón, señor.",
      "example_1": "Usted tiene razón, señor. (usted = 3ª persona)",
      "example_2": "",
      "explanation": "'Tienes' è la coniugazione di 'tú'. Con 'usted' ci vuole la 3ª persona: 'tiene'. Come in italiano: non si dice 'Lei hai' ma 'Lei ha'. L'errore viene dalla confusione tra la persona grammaticale e il referente ('usted' si riferisce a te, ma si coniuga come se fosse 'lui/lei')."
    },
    "levels": [
      {
        "level": 1,
        "label": "Usted = 3.ª persona",
        "translation": "Usted = 3ª persona",
        "examples": [
          {
            "original": "Usted habla muy bien.",
            "translation": "Lei parla molto bene.",
            "note": "'Habla' = 3ª persona di 'hablar'. Come in italiano 'Lei parla' usa la 3ª persona."
          },
          {
            "original": "¿Usted es el señor García?",
            "translation": "Lei è il signor García?",
            "note": "'Es' = 3ª persona di 'ser'. Come in italiano 'Lei è'. Corrispondenza perfetta."
          }
        ]
      },
      {
        "level": 2,
        "label": "Formas útiles con usted",
        "translation": "Forme utili con usted",
        "examples": [
          {
            "original": "Por favor, ¿puede ayudarme?",
            "translation": "Per favore, può aiutarmi?",
            "note": "'Puede' = 3ª persona di 'poder'. Come in italiano 'può'. Formula di cortesia molto utile."
          },
          {
            "original": "¿Cuánto cuesta, por favor?",
            "translation": "Quanto costa, per favore?",
            "note": "Quando 'usted' è implicito (stai parlando con un commesso), si omette il pronome ma si mantiene la coniugazione alla 3ª persona."
          }
        ]
      },
      {
        "level": 3,
        "label": "Usted con pronombres reflexivos",
        "translation": "Usted con pronomi riflessivi",
        "examples": [
          {
            "original": "¿Cómo se llama usted?",
            "translation": "Come si chiama?",
            "note": "Con 'usted', il pronome riflessivo diventa 'se' (3ª persona), non 'te'. Come in italiano 'Lei si chiama', non 'Lei ti chiami'. Corrispondenza perfetta!"
          },
          {
            "original": "¿Cómo se siente usted hoy?",
            "translation": "Come si sente oggi?",
            "note": "'Se siente' con usted — come 'si sente' con Lei in italiano. La logica è identica."
          }
        ]
      }
    ],
    "emoji": "👔",
    "phonetic": "",
    "translations": { "it": "Usted — la 3ª persona del rispetto" }
  },

  {
    "id": "es_a1_tuteo_usted_03",
    "type": "concept",
    "title": "Vosotros / Ustedes — il plurale del 'tú'",
    "bridge": "In italiano 'voi' fa tutto: informale e formale al plurale. In spagnolo della Penisola Iberica c'è una distinzione: 'vosotros' per il plurale informale e 'ustedes' per il formale. In America Latina, invece, 'ustedes' fa tutto, come il 'voi' italiano. Quindi se studi lo spagnolo latinoamericano, 'vosotros' non ti serve.",
    "rule": "In Spagna: 'vosotros/vosotras' (plurale informale) / 'ustedes' (plurale formale). In America Latina: solo 'ustedes' (formale e informale). 'Vosotros' ha coniugazione speciale: -áis, -éis, -ís.",
    "common_error": {
      "wrong": "Voi siete → Vosotros sois (corretto in Spagna) / Vosotros sois (strano in Messico)",
      "example_1": "Vosotros sois mis amigos. (Spagna, informale)",
      "example_2": "Ustedes son mis amigos. (America Latina, ovunque)",
      "explanation": "Usare 'vosotros' in America Latina suona antiquato e letterario, come se un italiano parlasse come nel '700. Se studi lo spagnolo per viaggiare in America Latina, impara solo 'ustedes'. Se studi per la Spagna, impara entrambe le forme."
    },
    "levels": [
      {
        "level": 1,
        "label": "Vosotros (España)",
        "translation": "Vosotros (Spagna)",
        "examples": [
          {
            "original": "¿Vosotros sois amigos?",
            "translation": "Voi siete amici?",
            "note": "'Sois' = forma di 'ser' per 'vosotros'. Usato in Spagna tra amici o coetanei."
          },
          {
            "original": "¿Tenéis hambre?",
            "translation": "Avete fame?",
            "note": "La terminazione '-éis' è la marca di 'vosotros' per i verbi in '-er'. Non esiste in italiano una forma analoga."
          }
        ]
      },
      {
        "level": 2,
        "label": "Ustedes (universal)",
        "translation": "Ustedes (universale)",
        "examples": [
          {
            "original": "¿Ustedes son de Italia?",
            "translation": "Voi siete dall'Italia?",
            "note": "'Ustedes' funziona ovunque. In America Latina è l'unica forma; in Spagna è la forma formale."
          },
          {
            "original": "¿Qué quieren ustedes tomar?",
            "translation": "Cosa vogliono ordinare?",
            "note": "'Quieren' = 3ª persona plurale. 'Ustedes' si coniuga come 'ellos/ellas'."
          }
        ]
      },
      {
        "level": 3,
        "label": "Comparativa de formas",
        "translation": "Confronto delle forme",
        "examples": [
          {
            "original": "Vosotros habláis / Ustedes hablan",
            "translation": "Voi parlate (Spagna, informale) / Voi parlate (America Latina)",
            "note": "Due coniugazioni per lo stesso significato. 'Habláis' con accento → vosotros; 'hablan' → ustedes. Se non sei sicuro, usa sempre 'ustedes hablan': funziona in tutto il mondo."
          },
          {
            "original": "¿Os gusta? / ¿Les gusta?",
            "translation": "Vi piace? (Spagna) / Vi piace? (America Latina)",
            "note": "Anche i pronomi cambiano: 'os' per vosotros, 'les' per ustedes. Due sistemi paralleli."
          }
        ]
      }
    ],
    "emoji": "👥",
    "phonetic": "",
    "translations": { "it": "Vosotros / Ustedes — il plurale di 'tu'" }
  },


  {
    "id": "es_a1_genero_01",
    "type": "concept",
    "title": "El género — maschile e femminile, come in italiano",
    "bridge": "Il genere grammaticale funziona in modo molto simile tra le due lingue: nomi, articoli e aggettivi si accordano tutti. La buona notizia: le regole spagnole sono ancora più regolari dell'italiano. Il rischio: assumere che il genere sia sempre identico all'italiano — non è così.",
    "rule": "Nomi e aggettivi in '-o' sono maschili; in '-a', femminili. L'aggettivo deve accordarsi in genere e numero con il nome. Impara ogni parola con il suo articolo, specialmente le eccezioni.",
    "common_error": {
      "wrong": "una chico simpático / un chica simpática",
      "example_1": "un chico simpático (maschile) / una chica simpática (femminile)",
      "example_2": "",
      "explanation": "Articolo, nome e aggettivo devono accordarsi tutti e tre. Se il nome è femminile, anche l'articolo e l'aggettivo devono essere femminili. È lo stesso sistema dell'italiano — solo i generi di alcune parole possono differire."
    },
    "levels": [
      {
        "level": 1,
        "label": "Adjetivos -o/-a",
        "translation": "Aggettivi -o/-a",
        "examples": [
          {
            "original": "un chico alto / una chica alta",
            "translation": "un ragazzo alto / una ragazza alta",
            "note": "'Alto' → maschile; 'alta' → femminile. Come in italiano, l'accordo è sistematico."
          },
          {
            "original": "un libro nuevo / una canción nueva",
            "translation": "un libro nuovo / una canzone nuova",
            "note": "L'accordo segue il genere del nome. Come in italiano 'nuovo/nuova'."
          }
        ]
      },
      {
        "level": 2,
        "label": "Adjetivos invariables",
        "translation": "Aggettivi invariabili",
        "examples": [
          {
            "original": "un hombre inteligente / una mujer inteligente",
            "translation": "un uomo intelligente / una donna intelligente",
            "note": "Gli aggettivi in '-e' non cambiano con il genere! Solo il plurale varia (-es). Come in italiano 'intelligente' per entrambi i generi."
          },
          {
            "original": "un coche azul / una moto azul",
            "translation": "una macchina azzurra / una moto azzurra",
            "note": "I colori che finiscono in consonante sono invariabili in genere. Diverso dall'italiano dove 'azzurro/azzurra' si accorda."
          }
        ]
      },
      {
        "level": 3,
        "label": "Concordancia en la frase completa",
        "translation": "Accordo nell'intera frase",
        "examples": [
          {
            "original": "La casa es pequeña y bonita.",
            "translation": "La casa è piccola e bella.",
            "note": "Tutti gli aggettivi nella frase si accordano con 'casa' (femminile): 'pequeña', 'bonita'. Come in italiano."
          },
          {
            "original": "Los niños están cansados.",
            "translation": "I bambini sono stanchi.",
            "note": "Al plurale maschile, l'accordo vale anche per l'aggettivo: 'cansados'. Come in italiano 'stanchi'."
          }
        ]
      }
    ],
    "emoji": "⚥",
    "phonetic": "",
    "translations": { "it": "Il genere — maschile e femminile, come in italiano" }
  },

  {
    "id": "es_a1_genero_02",
    "type": "concept",
    "title": "Sustantivos con género variable — stesso concetto, due forme",
    "bridge": "In italiano cambi la terminazione per indicare il genere: 'attore/attrice', 'amico/amica'. In spagnolo è ancora più regolare: quasi sempre si cambia solo '-o' in '-a'. La difficoltà sta nei nomi il cui genere non coincide con l'italiano.",
    "rule": "Per persone e animali, il genere del nome cambia spesso con la terminazione: -o (masch.) / -a (femm.). Alcuni nomi hanno forma completamente diversa. Altri sono identici per entrambi i generi.",
    "common_error": {
      "wrong": "Mi médica es muy bueno.",
      "example_1": "Mi médica es muy buena. (médica femminile → buena, anche femminile)",
      "example_2": "",
      "explanation": "Quando il nome è femminile ('médica'), tutti gli aggettivi che lo riguardano devono essere femminili ('buena'). L'accordo deve essere coerente in tutta la frase. Stessa regola dell'italiano — l'errore è tipicamente di distrazione."
    },
    "levels": [
      {
        "level": 1,
        "label": "Pares regulares -o/-a",
        "translation": "Coppie regolari -o/-a",
        "examples": [
          {
            "original": "el amigo / la amiga",
            "translation": "l'amico / l'amica",
            "note": "Cambio regolare -o/-a. Identico all'italiano! L'articolo cambia di conseguenza."
          },
          {
            "original": "el profesor / la profesora",
            "translation": "il professore / la professoressa",
            "note": "Per i nomi che finiscono in consonante, si aggiunge '-a' al femminile. Più regolare dell'italiano."
          }
        ]
      },
      {
        "level": 2,
        "label": "Formas completamente distintas",
        "translation": "Forme completamente diverse",
        "examples": [
          {
            "original": "el hombre / la mujer",
            "translation": "l'uomo / la donna",
            "note": "Due parole diverse — da memorizzare separatamente. Come in italiano."
          },
          {
            "original": "el padre / la madre",
            "translation": "il padre / la madre",
            "note": "Forme diverse per genere biologico. Come in italiano."
          }
        ]
      },
      {
        "level": 3,
        "label": "Sustantivos de género común",
        "translation": "Nomi a genere comune",
        "examples": [
          {
            "original": "el / la estudiante",
            "translation": "lo studente / la studentessa",
            "note": "Il nome non cambia! Solo l'articolo indica il genere. Come in italiano 'il/la cantante'. Frequente per nomi in '-ista', '-nte'."
          },
          {
            "original": "el / la periodista",
            "translation": "il giornalista / la giornalista",
            "note": "Stessa forma per entrambi i generi. L'accordo degli aggettivi rimane obbligatorio secondo il sesso della persona."
          }
        ]
      }
    ],
    "emoji": "🔄",
    "phonetic": "",
    "translations": { "it": "Nomi a genere variabile — stesso concetto, due forme" }
  },

  {
    "id": "es_a1_genero_03",
    "type": "concept",
    "title": "Generos distintos — cuando el español y el italiano no coinciden",
    "bridge": "La maggior parte dei generi coincide tra le due lingue, ma esistono differenze importanti che causano errori automatici. Vale la pena imparare le più frequenti esplicitamente, invece di scoprirle durante una conversazione.",
    "rule": "Non dare per scontato che il genere di una parola sia identico all'italiano. Impara le parole frequenti con il loro articolo fin dall'inizio. Le terminazioni '-dad', '-ción', '-sión' sono sempre femminili; '-ema', '-ama', '-apa' sono maschili.",
    "common_error": {
      "wrong": "la calor del verano (confuso con 'la calore')",
      "example_1": "el calor del verano (calor = maschile in spagnolo)",
      "example_2": "",
      "explanation": "In italiano 'il calore' è maschile — in spagnolo 'el calor' è anche maschile, quindi coincide! Ma l'errore tipico viene da parole come 'la sal' (femminile) vs 'il sale' (maschile in italiano), o 'el árbol' (maschile) vs 'l'albero' (maschile ✓). Sempre meglio verificare."
    },
    "levels": [
      {
        "level": 1,
        "label": "Generos que coinciden",
        "translation": "Generi che coincidono",
        "examples": [
          {
            "original": "el sol, la luna, el mar",
            "translation": "il sole, la luna, il mare",
            "note": "Questi tre coincidono con l'italiano! 'Il sole' → 'el sol' (masch.), 'la luna' → 'la luna' (femm.), 'il mare' → 'el mar' (masch.)."
          },
          {
            "original": "la mano, el problema",
            "translation": "la mano, il problema",
            "note": "'La mano' femminile in entrambe le lingue. 'El problema' maschile in entrambe (origine greca). Coincidono!"
          }
        ]
      },
      {
        "level": 2,
        "label": "Generos diferentes",
        "translation": "Generi diversi",
        "examples": [
          {
            "original": "la sal",
            "translation": "il sale → la sal (femminile!)",
            "note": "'Il sale' in italiano è maschile, 'la sal' in spagnolo è femminile. Uno dei casi di divergenza più frequente."
          },
          {
            "original": "el puente",
            "translation": "il ponte → el puente (maschile ✓)",
            "note": "Questo coincide! Maschile in entrambe le lingue. Usato come esempio per ricordare di verificare sempre."
          }
        ]
      },
      {
        "level": 3,
        "label": "Palabras que engañan",
        "translation": "Parole che ingannano",
        "examples": [
          {
            "original": "la leche",
            "translation": "il latte → la leche (femminile!)",
            "note": "'Il latte' in italiano è maschile, 'la leche' in spagnolo è femminile. Ingannevole perché la parola stessa è diversa."
          },
          {
            "original": "el árbol",
            "translation": "l'albero → el árbol (maschile ✓)",
            "note": "Coincide: maschile in entrambe le lingue. Finisce in '-l' → nessun segnale dalla terminazione — da memorizzare con l'articolo."
          }
        ]
      }
    ],
    "emoji": "🧩",
    "phonetic": "",
    "translations": { "it": "Generi diversi — quando le due lingue non coincidono" }
  },


  {
    "id": "es_a1_presente_gerundio_01",
    "type": "concept",
    "title": "Hablo vs. Estoy hablando — azione abituale o in corso?",
    "bridge": "Nella tua lingua hai la stessa distinzione: 'parlo' (abitudine) vs 'sto parlando' (azione in corso ora). In spagnolo è identico: 'hablo' per le abitudini, 'estoy hablando' per sottolineare che sta succedendo in questo momento. La struttura 'estar + gerundio' è la copia esatta di 'stare + gerundio' dell'italiano!",
    "rule": "Presente semplice (hablo) = abitudine, verità generale, futuro prossimo. Presente progressivo (estoy hablando) = azione in corso in questo preciso momento. In spagnolo il progressivo è usato meno dell'italiano per situazioni durature.",
    "common_error": {
      "wrong": "Sto vivendo a Madrid da tre anni. → Estoy viviendo en Madrid desde tres años.",
      "example_1": "Vivo en Madrid desde hace tres años. (stato continuo = presente semplice in spagnolo)",
      "example_2": "",
      "explanation": "In italiano 'sto vivendo' è accettabile per situazioni continue. In spagnolo, per situazioni durevoli (abitare, lavorare, studiare da un certo tempo) si usa il presente semplice, non il progressivo. 'Estoy viviendo' esiste ma è raro per situazioni stabili."
    },
    "levels": [
      {
        "level": 1,
        "label": "La diferencia básica",
        "translation": "La differenza di base",
        "examples": [
          {
            "original": "Hablo español.",
            "translation": "Parlo spagnolo. (competenza generale)",
            "note": "Presente semplice = competenza, abitudine, fatto generale. Come in italiano."
          },
          {
            "original": "Estoy hablando con mi jefe.",
            "translation": "Sto parlando con il mio capo. (adesso)",
            "note": "Presente progressivo = azione che si svolge in questo momento. Come 'sto parlando' in italiano. Struttura identica!"
          }
        ]
      },
      {
        "level": 2,
        "label": "Cuándo usar cada uno",
        "translation": "Quando usare l'uno o l'altro",
        "examples": [
          {
            "original": "Trabajo en una escuela.",
            "translation": "Lavoro in una scuola. (situazione abituale)",
            "note": "Presente semplice per situazioni stabili o abituali. Non 'estoy trabajando' qui — diverso dall'italiano dove 'sto lavorando' è più accettabile."
          },
          {
            "original": "¡Silencio! Estoy trabajando.",
            "translation": "Silenzio! Sto lavorando.",
            "note": "Progressivo per sottolineare l'azione in corso e interrotta. Come in italiano 'sto lavorando' per richiedere silenzio."
          }
        ]
      },
      {
        "level": 3,
        "label": "Diferencia clave con el italiano",
        "translation": "Differenza chiave con l'italiano",
        "examples": [
          {
            "original": "Estudio medicina.",
            "translation": "Studio medicina. (in modo generale)",
            "note": "In spagnolo il presente semplice basta per azioni in corso ma abituali. Il progressivo non è obbligatorio come in inglese, e meno diffuso che in italiano per situazioni durevoli."
          },
          {
            "original": "¿Qué estás haciendo?",
            "translation": "Cosa stai facendo?",
            "note": "Domanda sull'azione immediata → progressivo naturale. Come in italiano 'cosa stai facendo?'. Corrispondenza perfetta in questo caso."
          }
        ]
      }
    ],
    "emoji": "⏱️",
    "phonetic": "",
    "translations": { "it": "Parlo vs. Sto parlando" }
  },

  {
    "id": "es_a1_presente_gerundio_02",
    "type": "concept",
    "title": "El gerundio — cómo se forma (más fácil que en italiano)",
    "bridge": "In italiano il gerundio si forma con '-ando'/'-endo' (parlando, mangiando). In spagnolo è quasi identico: '-ando' per i verbi in '-ar' e '-iendo' per i verbi in '-er'/'-ir'. Probabilmente è la forma verbale più facile per te, perché la logica è la stessa!",
    "rule": "Gerundio: verbi in '-ar' → '-ando' (hablar → hablando). Verbi in '-er' e '-ir' → '-iendo' (comer → comiendo, vivir → viviendo). Sempre invariabile (non si accorda mai in genere o numero).",
    "common_error": {
      "wrong": "Sto mangiando → Estoy comiendo ✓ (corretto!) / Estoy mangiando ✗",
      "example_1": "Estoy comiendo. (comer → comiendo, non 'mangiando')",
      "example_2": "",
      "explanation": "La struttura è identica ('stare/estar + gerundio'), ma il gerundio si forma sulla radice spagnola, non italiana. Non si può usare il gerundio italiano con 'estar'. L'errore tipico è mescolare le due lingue."
    },
    "levels": [
      {
        "level": 1,
        "label": "Formación regular",
        "translation": "Formazione regolare",
        "examples": [
          {
            "original": "hablar → hablando",
            "translation": "parlare → parlando",
            "note": "Verbo in '-ar': togliere '-ar', aggiungere '-ando'. Come in italiano '-are' → '-ando'. Identico!"
          },
          {
            "original": "comer → comiendo",
            "translation": "mangiare → mangiando",
            "note": "Verbo in '-er': togliere '-er', aggiungere '-iendo'. Come in italiano '-ere'/'-ire' → '-endo/endo'."
          },
          {
            "original": "vivir → viviendo",
            "translation": "vivere → vivendo",
            "note": "Verbo in '-ir': togliere '-ir', aggiungere '-iendo'. Forma molto simile all'italiano 'vivendo'."
          }
        ]
      },
      {
        "level": 2,
        "label": "Gerundios irregulares comunes",
        "translation": "Gerundi irregolari comuni",
        "examples": [
          {
            "original": "decir → diciendo",
            "translation": "dire → dicendo",
            "note": "Verbo irregolare: 'e→i' nella radice. Simile all'italiano 'dicendo'."
          },
          {
            "original": "ir → yendo",
            "translation": "andare → andando",
            "note": "Molto irregolare. 'Yendo' non somiglia affatto all'italiano 'andando' — da memorizzare."
          },
          {
            "original": "leer → leyendo",
            "translation": "leggere → leggendo",
            "note": "'iendo' → 'yendo' quando due vocali si incontrano. Cambiamento ortografico regolare."
          }
        ]
      },
      {
        "level": 3,
        "label": "El gerundio con pronombres",
        "translation": "Il gerundio con i pronomi",
        "examples": [
          {
            "original": "Estoy escuchándote. / Te estoy escuchando.",
            "translation": "Ti sto ascoltando.",
            "note": "Il pronome può attaccarsi alla fine del gerundio (con accento) oppure andare prima di 'estoy'. Entrambe le forme sono corrette. Come in italiano 'ti sto ascoltando' o 'sto ascoltandoti'."
          },
          {
            "original": "Está haciéndolo.",
            "translation": "Lo sta facendo.",
            "note": "Quando il pronome si attacca, l'accento scritto appare per mantenere la pronuncia originale. Come in italiano 'facendolo'."
          }
        ]
      }
    ],
    "emoji": "🔧",
    "phonetic": "",
    "translations": { "it": "Il gerundio — come si forma" }
  },

  {
    "id": "es_a1_presente_gerundio_03",
    "type": "concept",
    "title": "Estoy hablando — quando usarlo davvero",
    "bridge": "In italiano usi 'stare + gerundio' abbastanza spesso, anche per situazioni durevoli ('sto vivendo a Roma da tre anni'). In spagnolo il progressivo è più ristretto: solo per azioni che si svolgono in questo preciso istante. Per tutto il resto — abitudini, stati, situazioni stabili — si usa il presente semplice.",
    "rule": "Usa 'estar + gerundio' per: azione in corso nel momento in cui parli, descrizione di una scena in diretta, o per enfatizzare l'immediatezza. Non usarlo per abitudini, stati duraturi o il futuro.",
    "common_error": {
      "wrong": "Sempre sto arrivando in ritardo. → Siempre estoy llegando tarde.",
      "example_1": "Siempre llego tarde. (abitudine = presente semplice)",
      "example_2": "Estoy llegando ahora mismo. (azione nell'istante preciso = progressivo)",
      "explanation": "'Siempre' (sempre) segnala un'abitudine → presente semplice obbligatorio. Il progressivo non si usa per le abitudini in spagnolo, anche quando si usano 'sempre' o 'di solito'. Diverso dall'italiano dove 'sto sempre arrivando tardi' è possibile (anche se colloquiale)."
    },
    "levels": [
      {
        "level": 1,
        "label": "Describir lo que pasa ahora",
        "translation": "Descrivere quello che succede ora",
        "examples": [
          {
            "original": "Está lloviendo.",
            "translation": "Sta piovendo.",
            "note": "Meteo in diretta → progressivo naturale. Come in italiano 'sta piovendo'. Corrispondenza perfetta!"
          },
          {
            "original": "Los niños están durmiendo.",
            "translation": "I bambini stanno dormendo.",
            "note": "Scena descritta nel momento in cui si parla → progressivo. Come in italiano."
          }
        ]
      },
      {
        "level": 2,
        "label": "Interrupciones y contexto",
        "translation": "Interruzioni e contesto",
        "examples": [
          {
            "original": "No puedo hablar, estoy conduciendo.",
            "translation": "Non posso parlare, sto guidando.",
            "note": "Giustificazione con un'azione immediata → progressivo perfetto. Come in italiano 'sto guidando'. Identico!"
          },
          {
            "original": "¿Qué estás haciendo?",
            "translation": "Cosa stai facendo?",
            "note": "Domanda sull'azione immediata → progressivo. Corrispondenza perfetta con l'italiano."
          }
        ]
      },
      {
        "level": 3,
        "label": "Cuándo NO usar el progresivo",
        "translation": "Quando NON usare il progressivo",
        "examples": [
          {
            "original": "Vivo en Barcelona. (no: Estoy viviendo en Barcelona)",
            "translation": "Vivo a Barcellona.",
            "note": "Residenza = stato continuo → presente semplice. In italiano 'sto vivendo a Barcellona' è possibile; in spagnolo è raro e suona strano per situazioni stabili."
          },
          {
            "original": "¿Qué haces mañana? (no: ¿Qué estás haciendo mañana?)",
            "translation": "Cosa fai domani?",
            "note": "Per il futuro prossimo, lo spagnolo preferisce il presente semplice. Il progressivo rimane ancorato all'istante presente, non al futuro."
          }
        ]
      }
    ],
    "emoji": "🎬",
    "phonetic": "",
    "translations": { "it": "Estoy hablando — quando usarlo davvero" }
  }

]
