[
  {
    "id": "da_A1_func_01",
    "type": "concept",
    "category": "Funktionskommunikation",
    "title": "Greet and introduce yourself",
    "bridge": "P√• dansk siger vi 'Jeg hedder...' eller 'Jeg er...' for at pr√¶sentere os. P√• engelsk er det 'My name is...' eller 'I am...'. Den st√łrste forskel er, at danskere ofte overs√¶tter 'Jeg hedder...' til 'I name...' eller 'I am called...', hvilket lyder unaturligt p√• engelsk. 'I am called' er korrekt, men meget formelt og bruges sj√¶ldent i daglig tale. Det bedste er at bruge 'My name is...' eller 'I am...'.",
    "rule": "Til at hilse: 'Hello' (Hej), 'Hi' (mere uformelt), 'Good morning' (God morgen), 'Good afternoon' (God eftermiddag), 'Good evening' (God aften). Til at pr√¶sentere sig selv: 'My name is...' (Jeg hedder...) eller 'I am...' (Jeg er...). Til at sp√łrge om navn: 'What is your name?' (Hvad hedder du?). Til at svare p√• en hilsen: 'Nice to meet you' (Dejligt at m√łde dig) og svaret er 'Nice to meet you too'. Til afsked: 'Goodbye', 'Bye', 'See you later'.",
    "concept_examples": [
      {
        "text": "Hello, my name is Maria.",
        "translation": "Hej, jeg hedder Maria.",
        "phonetic": "/h…ôňąl…ô ä ma…™ ne…™m …™z m…ôňąriňź…ô/"
      },
      {
        "text": "Good morning, I am Peter.",
        "translation": "God morgen, jeg er Peter.",
        "phonetic": "/…° äd ňąm…Ēňźn…™Ňč a…™ √¶m ňąpiňźt…ô/"
      },
      {
        "text": "Nice to meet you.",
        "translation": "Dejligt at m√łde dig.",
        "phonetic": "/na…™s t…ô miňźt juňź/"
      },
      {
        "text": "What is your name?",
        "translation": "Hvad hedder du?",
        "phonetic": "/w…ít …™z j…Ēňź ne…™m/"
      }
    ],
    "common_error": {
      "wrong": "I name Daniel.",
      "correct": "My name is Daniel.",
      "correct_alt": "I am Daniel.",
      "explanation": "P√• dansk siger vi 'Jeg hedder Daniel' ‚Äď ordret oversat bliver det 'I name Daniel' eller 'I am called Daniel'. Det er en direkte overs√¶ttelse, der lyder unaturlig p√• engelsk. Brug 'My name is...' eller 'I am...' i stedet."
    },
    "levels": [
      {
        "level": 1,
        "label": "Basic greeting",
        "translation": "Grundl√¶ggende hilsen",
        "examples": [
          {
            "original": "Hello!",
            "phonetic": "/h…ôňąl…ô ä/",
            "translation": "Hej!",
            "note": "Standardhilsen."
          }
        ]
      },
      {
        "level": 2,
        "label": "Introduce yourself",
        "translation": "Pr√¶senter dig selv",
        "examples": [
          {
            "original": "My name is John.",
            "phonetic": "/ma…™ ne…™m …™z d í…ín/",
            "translation": "Jeg hedder John.",
            "note": "Den mest almindelige m√•de at sige sit navn p√•."
          }
        ]
      },
      {
        "level": 3,
        "label": "Ask someone's name",
        "translation": "Sp√łrg om navn",
        "examples": [
          {
            "original": "What is your name?",
            "phonetic": "/w…ít …™z j…Ēňź ne…™m/",
            "translation": "Hvad hedder du?",
            "note": "Direkte sp√łrgsm√•l for at f√• navnet at vide."
          }
        ]
      },
      {
        "level": 4,
        "label": "Farewell",
        "translation": "Afsked",
        "examples": [
          {
            "original": "See you tomorrow!",
            "phonetic": "/siňź juňź t…ôňąm…ír…ô ä/",
            "translation": "Vi ses i morgen!",
            "note": "Uformel afsked."
          }
        ]
      }
    ],
    "conversation": {
      "vocabulary": [],
      "dialogue": []
    }
  },
  {
    "id": "da_A1_func_02",
    "type": "concept",
    "category": "Funktionskommunikation",
    "title": "Give personal information (age, nationality, profession)",
    "bridge": "P√• dansk siger vi 'Jeg er 20 √•r' for alder (uden 'gammel'), 'Jeg er dansk' for nationalitet og 'Jeg er l√¶rer' for erhverv (uden artikel). P√• engelsk er det anderledes: for alder skal man tilf√łje 'old' ('I am 20 years old'), for erhverv skal man bruge 'a' eller 'an' ('I am a teacher'). Nationalitet er derimod ligesom p√• dansk ‚Äď ingen artikel ('I am Danish'). Husk altid at bruge 'to be' til alder og erhverv, ikke 'have'.",
    "rule": "Til alder: 'I am [number] years old' (f.eks. I am 25 years old). Til nationalitet: 'I am [nationality]' (f.eks. I am Danish, I am Mexican). Til erhverv: 'I am a/an [profession]' (f.eks. I am a doctor, I am an engineer). Til at sp√łrge: 'How old are you?' (Hvor gammel er du?), 'Where are you from?' (Hvor kommer du fra?), 'What do you do?' (Hvad laver du?) eller 'What is your job?'.",
    "concept_examples": [
      {
        "text": "I am 25 years old.",
        "translation": "Jeg er 25 √•r gammel.",
        "phonetic": "/a…™ √¶m ňątwenti fa…™v j…™…ôz …ô äld/"
      },
      {
        "text": "I am Danish.",
        "translation": "Jeg er dansk.",
        "phonetic": "/a…™ √¶m ňąde…™n…™ É/"
      },
      {
        "text": "I am a teacher.",
        "translation": "Jeg er l√¶rer.",
        "phonetic": "/a…™ √¶m …ô ňątiňźt É…ô/"
      },
      {
        "text": "How old are you?",
        "translation": "Hvor gammel er du?",
        "phonetic": "/ha ä …ô äld …Ďňźr juňź/"
      }
    ],
    "common_error": {
      "wrong": "I have 25 years.",
      "correct": "I am 25 years old.",
      "correct_alt": "",
      "explanation": "P√• dansk siger vi 'Jeg er 25 √•r' ‚Äď det er en direkte overs√¶ttelse, hvor man glemmer 'old' til sidst. P√• engelsk skal man altid inkludere 'old', n√•r man angiver alder."
    },
    "levels": [
      {
        "level": 1,
        "label": "Age",
        "translation": "Alder",
        "examples": [
          {
            "original": "I am 30 years old.",
            "phonetic": "/a…™ √¶m ňąőł…úňźti j…™…ôz …ô äld/",
            "translation": "Jeg er 30 √•r gammel.",
            "note": "Brug 'to be' til alder."
          }
        ]
      },
      {
        "level": 2,
        "label": "Nationality",
        "translation": "Nationalitet",
        "examples": [
          {
            "original": "I am Mexican.",
            "phonetic": "/a…™ √¶m ňąmeks…™k…ôn/",
            "translation": "Jeg er mexicaner.",
            "note": "Ingen artikel for nationalitet."
          }
        ]
      },
      {
        "level": 3,
        "label": "Profession",
        "translation": "Erhverv",
        "examples": [
          {
            "original": "She is a nurse.",
            "phonetic": "/ Éiňź …™z …ô n…úňźs/",
            "translation": "Hun er sygeplejerske.",
            "note": "Med artikel 'a' eller 'an' for erhverv."
          }
        ]
      },
      {
        "level": 4,
        "label": "Questions",
        "translation": "Sp√łrgsm√•l",
        "examples": [
          {
            "original": "Where are you from?",
            "phonetic": "/we…ô …Ďňźr juňź fr…ím/",
            "translation": "Hvor kommer du fra?",
            "note": "Sp√łrgsm√•l om oprindelse."
          }
        ]
      }
    ],
    "conversation": {
      "vocabulary": [],
      "dialogue": []
    }
  },
  {
    "id": "da_A1_func_03",
    "type": "concept",
    "category": "Funktionskommunikation",
    "title": "Describe objects and people (basic)",
    "bridge": "P√• dansk placerer vi adjektivet F√ėR substantivet: 'en r√łd bil', 'en stor hund'. P√• engelsk er det pr√¶cis det samme: 'a red car', 'a big dog'. Der er alts√• INGEN forskel i ordstilling mellem dansk og engelsk, n√•r det g√¶lder adjektiver. Dette er en lettelse for danskere ‚Äď I beh√łver ikke at l√¶re noget nyt her! Brug 'to be' til generelle beskrivelser (She is tall) og 'have got' til fysiske egenskaber (She has got blue eyes).",
    "rule": "Til at beskrive: 1) Adjektiv + substantiv (a big house). 2) Subjekt + verb 'to be' + adjektiv (The house is big). 3) Subjekt + 'have/has got' + egenskab (She has got long hair). Almindelige adjektiver: big (stor), small (lille), tall (h√łj), short (kort/lav), beautiful (smuk), old (gammel), young (ung), fast (hurtig), slow (langsom).",
    "concept_examples": [
      {
        "text": "This is a big house.",
        "translation": "Det her er et stort hus.",
        "phonetic": "/√į…™s …™z …ô b…™…° ha äs/"
      },
      {
        "text": "She is tall and thin.",
        "translation": "Hun er h√łj og tynd.",
        "phonetic": "/ Éiňź …™z t…Ēňźl √¶nd őł…™n/"
      },
      {
        "text": "He has got blue eyes.",
        "translation": "Han har bl√• √łjne.",
        "phonetic": "/hiňź h√¶z …°…ít bluňź a…™z/"
      },
      {
        "text": "The car is red.",
        "translation": "Bilen er r√łd.",
        "phonetic": "/√į…ô k…Ďňźr …™z red/"
      }
    ],
    "common_error": {
      "wrong": "a car red",
      "correct": "a red car",
      "correct_alt": "",
      "explanation": "Denne fejl er mere almindelig for spansktalende, men danskere laver den sj√¶ldent, fordi dansk og engelsk har samme ordstilling (adjektiv f√łr substantiv). Men det er godt at minde om, at det er pr√¶cis som p√• dansk."
    },
    "levels": [
      {
        "level": 1,
        "label": "Adjective + noun",
        "translation": "Adjektiv + substantiv",
        "examples": [
          {
            "original": "a small dog",
            "phonetic": "/…ô sm…Ēňźl d…í…°/",
            "translation": "en lille hund",
            "note": "Adjektivet placeres f√łr substantivet ‚Äď ligesom p√• dansk."
          }
        ]
      },
      {
        "level": 2,
        "label": "Subject + to be + adjective",
        "translation": "Subjekt + to be + adjektiv",
        "examples": [
          {
            "original": "The book is interesting.",
            "phonetic": "/√į…ô b äk …™z ňą…™ntr…ôst…™Ňč/",
            "translation": "Bogen er interessant.",
            "note": "Brug 'to be' til generelle beskrivelser."
          }
        ]
      },
      {
        "level": 3,
        "label": "have/has got for features",
        "translation": "have/has got til egenskaber",
        "examples": [
          {
            "original": "She has got curly hair.",
            "phonetic": "/ Éiňź h√¶z …°…ít ňąk…úňźli he…ô/",
            "translation": "Hun har kr√łllet h√•r.",
            "note": "Brug 'have got' til fysiske egenskaber."
          }
        ]
      },
      {
        "level": 4,
        "label": "Combined description",
        "translation": "Kombineret beskrivelse",
        "examples": [
          {
            "original": "My brother is young and he has got green eyes.",
            "phonetic": "/ma…™ ňąbr Ć√į…ô …™z j ĆŇč √¶nd hiňź h√¶z …°…ít …°riňźn a…™z/",
            "translation": "Min bror er ung og han har gr√łnne √łjne.",
            "note": "Kombination af 'to be' og 'have got'."
          }
        ]
      }
    ],
    "conversation": {
      "vocabulary": [],
      "dialogue": []
    }
  },
  {
    "id": "da_A1_func_04",
    "type": "concept",
    "category": "Funktionskommunikation",
    "title": "Talk about daily routines",
    "bridge": "P√• dansk bruger vi nutid til at tale om rutiner: 'Jeg st√•r op klokken syv hver dag'. P√• engelsk er det pr√¶cis det samme ‚Äď vi bruger present simple til vaner og rutiner. Forskellen er, at p√• dansk bruger vi samme verbumform for alle personer, mens engelsk tilf√łjer -s i tredje person ental (he, she, it). Desuden bruger engelsk pr√¶positionsudtryk som 'at' til tider ('at 7 o'clock'), 'in' til dele af dagen ('in the morning') og 'on' til dage ('on Monday'). Husk, at danskere ofte glemmer -s i tredje person og placerer tidsudtryk forkert.",
    "rule": "Til at tale om rutiner: 1) Brug present simple (I get up, she works). 2) Brug tidsudtryk: 'at' + tid (at 8 am), 'in' + del af dag (in the morning), 'on' + dag (on Friday). 3) Brug frekvensadverbier f√łr verbet (I always eat breakfast). 4) Til at sp√łrge: 'What time do you get up?' eller 'When do you have lunch?'.",
    "concept_examples": [
      {
        "text": "I get up at 7 o'clock.",
        "translation": "Jeg st√•r op klokken syv.",
        "phonetic": "/a…™ …°et  Ćp √¶t ňąsev…ôn …ôňąkl…ík/"
      },
      {
        "text": "She usually has breakfast at 8 am.",
        "translation": "Hun plejer at spise morgenmad klokken otte om morgenen.",
        "phonetic": "/ Éiňź ňąjuňź íu…ôli h√¶z ňąbrekf…ôst √¶t e…™t √¶m/"
      },
      {
        "text": "We go to work at 9 in the morning.",
        "translation": "Vi tager p√• arbejde klokken ni om morgenen.",
        "phonetic": "/wiňź …°…ô ä t…ô w…úňźk √¶t na…™n …™n √į…ô ňąm…Ēňźn…™Ňč/"
      },
      {
        "text": "What time do you have dinner?",
        "translation": "Hvad tid spiser du middag?",
        "phonetic": "/w…ít ta…™m duňź juňź h√¶v ňąd…™n…ô/"
      }
    ],
    "common_error": {
      "wrong": "I eat now.",
      "correct": "I am eating now.",
      "correct_alt": "",
      "explanation": "P√• dansk bruger vi nutid ogs√• til handlinger, der foreg√•r lige nu: 'jeg spiser nu'. P√• engelsk skal man bruge present continuous (I am eating) til handlinger, der foreg√•r lige nu. Dette er en meget almindelig interferens fra dansk, som ikke har denne distinktion."
    },
    "levels": [
      {
        "level": 1,
        "label": "Daily actions",
        "translation": "Daglige handlinger",
        "examples": [
          {
            "original": "I get up early.",
            "phonetic": "/a…™ …°et  Ćp ňą…úňźli/",
            "translation": "Jeg st√•r tidligt op.",
            "note": "Verb i present simple til rutine."
          }
        ]
      },
      {
        "level": 2,
        "label": "Time expressions",
        "translation": "Tidsudtryk",
        "examples": [
          {
            "original": "I have lunch at 1 pm.",
            "phonetic": "/a…™ h√¶v l Ćnt É √¶t w Ćn piňź em/",
            "translation": "Jeg spiser frokost klokken et om eftermiddagen.",
            "note": "Brug 'at' til specifikke tider."
          }
        ]
      },
      {
        "level": 3,
        "label": "Frequency adverbs",
        "translation": "Frekvensadverbier",
        "examples": [
          {
            "original": "She never drinks coffee.",
            "phonetic": "/ Éiňź ňąnev…ô dr…™Ňčks ňąk…ífi/",
            "translation": "Hun drikker aldrig kaffe.",
            "note": "Adverbium f√łr hovedverbet."
          }
        ]
      },
      {
        "level": 4,
        "label": "Questions about routines",
        "translation": "Sp√łrgsm√•l om rutiner",
        "examples": [
          {
            "original": "What time do you go to bed?",
            "phonetic": "/w…ít ta…™m duňź juňź …°…ô ä t…ô bed/",
            "translation": "Hvad tid g√•r du i seng?",
            "note": "Sp√łrgsm√•l med 'what time' + do/does."
          }
        ]
      }
    ],
    "conversation": {
      "vocabulary": [],
      "dialogue": []
    }
  },
  {
    "id": "da_A1_func_05",
    "type": "concept",
    "category": "Funktionskommunikation",
    "title": "Express likes and dislikes (I like / I don't like)",
    "bridge": "P√• dansk siger vi 'Jeg kan godt lide pizza' eller 'Jeg kan lide pizza'. P√• engelsk bruger vi verbet 'like' p√• samme m√•de: 'I like pizza'. Forskellen er, at danskere nogle gange overs√¶tter 'kan godt lide' til 'can like' eller 'good like', hvilket bliver forkert. En anden almindelig interferens er at placere 'very much' mellem verbet og objektet: 'I like very much pizza' i stedet for 'I like pizza very much'. Husk ogs√•, at i tredje person ental (he, she, it) tilf√łjes -s: 'She likes pizza'.",
    "rule": "Til at udtrykke synes godt om: 1) Bekr√¶ftende: I/you/we/they like + objekt (I like coffee). He/she/it likes + objekt (She likes coffee). 2) Ben√¶gtende: I/you/we/they don't like (I don't like tea). He/she/it doesn't like (He doesn't like tea). 3) Sp√łrgsm√•l: Do you like...? (Kan du lide...?), Does she like...? (Kan hun lide...?). 4) Til at forst√¶rke: 'I like it very much' (Jeg kan rigtig godt lide det) eller 'I really like it'.",
    "concept_examples": [
      {
        "text": "I like pizza.",
        "translation": "Jeg kan godt lide pizza.",
        "phonetic": "/a…™ la…™k ňąpiňźts…ô/"
      },
      {
        "text": "She likes reading.",
        "translation": "Hun kan godt lide at l√¶se.",
        "phonetic": "/ Éiňź la…™ks ňąriňźd…™Ňč/"
      },
      {
        "text": "We don't like fast food.",
        "translation": "Vi kan ikke lide fastfood.",
        "phonetic": "/wiňź d…ô änt la…™k f…Ďňźst fuňźd/"
      },
      {
        "text": "Do you like music?",
        "translation": "Kan du lide musik?",
        "phonetic": "/duňź juňź la…™k ňąmjuňźz…™k/"
      }
    ],
    "common_error": {
      "wrong": "I like very much pizza.",
      "correct": "I like pizza very much.",
      "correct_alt": "",
      "explanation": "P√• dansk siger vi 'Jeg kan godt lide pizza meget' ‚Äď adverbet kommer efter objektet. P√• engelsk placeres 'very much' i slutningen af s√¶tningen, ikke mellem verbet og objektet. Dette er en direkte overs√¶ttelse fra dansk, der ofte forekommer."
    },
    "levels": [
      {
        "level": 1,
        "label": "Affirmative with I/you/we/they",
        "translation": "Bekr√¶ftende med I/you/we/they",
        "examples": [
          {
            "original": "I like chocolate.",
            "phonetic": "/a…™ la…™k ňąt É…ík…ôl…ôt/",
            "translation": "Jeg kan godt lide chokolade.",
            "note": "Verbet 'like' i grundform."
          }
        ]
      },
      {
        "level": 2,
        "label": "Affirmative with he/she/it",
        "translation": "Bekr√¶ftende med he/she/it",
        "examples": [
          {
            "original": "He likes football.",
            "phonetic": "/hiňź la…™ks ňąf ätb…Ēňźl/",
            "translation": "Han kan godt lide fodbold.",
            "note": "Tilf√łj -s i tredje person ental."
          }
        ]
      },
      {
        "level": 3,
        "label": "Negative with don't/doesn't",
        "translation": "Ben√¶gtende med don't/doesn't",
        "examples": [
          {
            "original": "She doesn't like coffee.",
            "phonetic": "/ Éiňź ňąd Ćznt la…™k ňąk…ífi/",
            "translation": "Hun kan ikke lide kaffe.",
            "note": "Brug 'doesn't' + verb i grundform."
          }
        ]
      },
      {
        "level": 4,
        "label": "Questions with Do/Does",
        "translation": "Sp√łrgsm√•l med Do/Does",
        "examples": [
          {
            "original": "Do you like dogs?",
            "phonetic": "/duňź juňź la…™k d…í…°z/",
            "translation": "Kan du lide hunde?",
            "note": "Sp√łrgsm√•l med 'do' + subjekt + verb i grundform."
          }
        ]
      }
    ],
    "conversation": {
      "vocabulary": [],
      "dialogue": []
    }
  },
  {
    "id": "da_A1_func_06",
    "type": "concept",
    "category": "Funktionskommunikation",
    "title": "Ask for and give prices",
    "bridge": "P√• dansk sp√łrger vi 'Hvor meget koster det?' eller 'Hvad koster den?'. P√• engelsk bruger vi 'How much is it?' (ental) eller 'How much are they?' (flertal). Man kan ogs√• sige 'How much does it cost?' (Hvor meget koster det?). Forskellen er, at p√• dansk bruger vi intet hj√¶lpeverbum, men p√• engelsk skal man bruge 'to be' eller hj√¶lpeverbet 'does' med 'cost'. Danskere har tendens til at sige 'How much cost it?' ‚Äď en direkte overs√¶ttelse uden hj√¶lpeverbum, hvilket er forkert.",
    "rule": "Til at sp√łrge om prisen: 1) 'How much is it?' (til et objekt) eller 'How much are they?' (til flere). 2) 'How much does it cost?' (Hvor meget koster den?). 3) 'How much is the T-shirt?' (Hvor meget koster T-shirten?). Til at svare: 'It is 25 dollars' eller 'It costs 25 dollars'. I sp√łrgsm√•l bruger man altid 'to be' eller hj√¶lpeverbet 'does' + 'cost'.",
    "concept_examples": [
      {
        "text": "How much is it?",
        "translation": "Hvor meget koster den?",
        "phonetic": "/ha ä m Ćt É …™z …™t/"
      },
      {
        "text": "How much does it cost?",
        "translation": "Hvor meget koster det?",
        "phonetic": "/ha ä m Ćt É d Ćz …™t k…íst/"
      },
      {
        "text": "It is 10 dollars.",
        "translation": "Det koster 10 dollars.",
        "phonetic": "/…™t …™z ten ňąd…íl…ôz/"
      },
      {
        "text": "How much are these shoes?",
        "translation": "Hvor meget koster de her sko?",
        "phonetic": "/ha ä m Ćt É …Ďňźr √įiňźz  Éuňźz/"
      }
    ],
    "common_error": {
      "wrong": "How much cost it?",
      "correct": "How much does it cost?",
      "correct_alt": "How much is it?",
      "explanation": "P√• dansk sp√łrger vi 'Hvor meget koster det?' uden hj√¶lpeverbum. P√• engelsk, med verbet 'cost', skal man bruge hj√¶lpeverbet 'does' i sp√łrgsm√•l. Dette er en almindelig direkte overs√¶ttelse fra dansk."
    },
    "levels": [
      {
        "level": 1,
        "label": "Ask price with 'to be'",
        "translation": "Sp√łrg om pris med 'to be'",
        "examples": [
          {
            "original": "How much is the book?",
            "phonetic": "/ha ä m Ćt É …™z √į…ô b äk/",
            "translation": "Hvor meget koster bogen?",
            "note": "Brug 'to be' til at sp√łrge om prisen."
          }
        ]
      },
      {
        "level": 2,
        "label": "Ask price with 'cost'",
        "translation": "Sp√łrg om pris med 'cost'",
        "examples": [
          {
            "original": "How much does the bag cost?",
            "phonetic": "/ha ä m Ćt É d Ćz √į…ô b√¶…° k…íst/",
            "translation": "Hvor meget koster tasken?",
            "note": "Brug 'does' + 'cost' til at sp√łrge."
          }
        ]
      },
      {
        "level": 3,
        "label": "Give price",
        "translation": "Giv prisen",
        "examples": [
          {
            "original": "It costs 5 euros.",
            "phonetic": "/…™t k…ísts fa…™v ňąj ä…ôr…ô äz/",
            "translation": "Det koster 5 euro.",
            "note": "Brug 'costs' i tredje person ental."
          }
        ]
      },
      {
        "level": 4,
        "label": "Plural questions",
        "translation": "Flertalssp√łrgsm√•l",
        "examples": [
          {
            "original": "How much are these apples?",
            "phonetic": "/ha ä m Ćt É …Ďňźr √įiňźz ňą√¶p…ôlz/",
            "translation": "Hvor meget koster de her √¶bler?",
            "note": "Brug 'are' til flertal."
          }
        ]
      }
    ],
    "conversation": {
      "vocabulary": [],
      "dialogue": []
    }
  },
  {
    "id": "da_A1_func_07",
    "type": "concept",
    "category": "Funktionskommunikation",
    "title": "Indicate location of places",
    "bridge": "P√• dansk bruger vi 'ligger' til faste steder (f.eks. 'Banken ligger n√¶r parken'). P√• engelsk bruger vi 'is' til al placering. Det er en vigtig forskel: danskere overs√¶tter ofte 'ligger' til 'lies', hvilket lyder meget formelt og unaturligt p√• engelsk ('The bank lies near the park'). Det bedre er at bruge 'is' ('The bank is near the park'). En anden forskel er pr√¶positioner: p√• dansk siger vi 'i skolen' for at vi er i bygningen, men p√• engelsk siger man 'at school' for at man studerer der, og 'in the school' for at man er inde i bygningen. Husk: til kollektiv transport bruger vi 'on' (on the bus), ikke 'in' ‚Äď modsat dansk, hvor vi siger 'i bussen'.",
    "rule": "Til at angive sted: 1) Brug verbet 'to be' (The bank is...). 2) Pr√¶positioner: 'on' (p√•, p√• en overflade eller gade), 'in' (i, indenfor), 'at' (ved, p√• et specifikt sted), 'next to' (ved siden af), 'near' (n√¶r), 'opposite' (over for), 'behind' (bagved), 'in front of' (foran). 3) Til at sp√łrge: 'Where is the...?' (Hvor ligger...?) eller 'Is there a... near here?' (Er der en... i n√¶rheden?).",
    "concept_examples": [
      {
        "text": "The supermarket is near the park.",
        "translation": "Supermarkedet ligger n√¶r parken.",
        "phonetic": "/√į…ô ňąsuňźp…ôm…Ďňźk…™t …™z n…™…ô √į…ô p…Ďňźk/"
      },
      {
        "text": "The school is next to the church.",
        "translation": "Skolen ligger ved siden af kirken.",
        "phonetic": "/√į…ô skuňźl …™z nekst t…ô √į…ô t É…úňźt É/"
      },
      {
        "text": "The pharmacy is on Main Street.",
        "translation": "Apoteket ligger p√• Main Street.",
        "phonetic": "/√į…ô ňąf…Ďňźm…ôsi …™z …ín me…™n striňźt/"
      },
      {
        "text": "Where is the bus station?",
        "translation": "Hvor ligger busstationen?",
        "phonetic": "/we…ô …™z √į…ô b Ćs ňąste…™ É…ôn/"
      }
    ],
    "common_error": {
      "wrong": "The bank lies near the park.",
      "correct": "The bank is near the park.",
      "correct_alt": "",
      "explanation": "P√• dansk siger vi 'banken ligger n√¶r parken' ‚Äď 'ligger' overs√¶ttes ofte til 'lies' af danskere. P√• engelsk bruger man n√¶sten altid 'is' til placering, og 'lies' lyder meget formelt eller poetisk. Brug 'is' i dagligdags sammenh√¶nge."
    },
    "levels": [
      {
        "level": 1,
        "label": "Basic location with 'in'",
        "translation": "Grundl√¶ggende sted med 'in'",
        "examples": [
          {
            "original": "The cat is in the garden.",
            "phonetic": "/√į…ô k√¶t …™z …™n √į…ô ňą…°…Ďňźd…ôn/",
            "translation": "Katten er i haven.",
            "note": "Brug 'in' til lukkede rum."
          }
        ]
      },
      {
        "level": 2,
        "label": "Location with 'next to'",
        "translation": "Sted med 'next to'",
        "examples": [
          {
            "original": "The restaurant is next to the hotel.",
            "phonetic": "/√į…ô ňąrestr…ínt …™z nekst t…ô √į…ô h…ô äňątel/",
            "translation": "Restauranten ligger ved siden af hotellet.",
            "note": "Brug 'next to' til sideposition."
          }
        ]
      },
      {
        "level": 3,
        "label": "Location with 'near' and 'opposite'",
        "translation": "Sted med 'near' og 'opposite'",
        "examples": [
          {
            "original": "The bank is opposite the park.",
            "phonetic": "/√į…ô b√¶Ňčk …™z ňą…íp…ôz…™t √į…ô p…Ďňźk/",
            "translation": "Banken ligger over for parken.",
            "note": "Brug 'opposite' til over for."
          }
        ]
      },
      {
        "level": 4,
        "label": "Question with Where",
        "translation": "Sp√łrgsm√•l med Where",
        "examples": [
          {
            "original": "Where is the police station?",
            "phonetic": "/we…ô …™z √į…ô p…ôňąliňźs ňąste…™ É…ôn/",
            "translation": "Hvor ligger politistationen?",
            "note": "Direkte sp√łrgsm√•l med 'Where'."
          }
        ]
      }
    ],
    "conversation": {
      "vocabulary": [],
      "dialogue": []
    }
  }
]